{
  "kusama": [
    {
      "minmax": [
         0,
        1006
      ],
      "types": {
        "signature": "(Address, AnySignature, SignedExtra)",
        "Address": "AccountId",
        "AccountIndex": "u32",
        "AccountId": "[u8; 32]",
        "AnySignature": "H512",
        "SignedExtra": "(OnlyStakingAndClaims, system::CheckVersion<Runtime>, system::CheckGenesis<Runtime>, system::CheckEra<Runtime>, system::CheckNonce<Runtime>, system::CheckWeight<Runtime>, balances::TakeFees<Runtime>)"
      }
    },
    {
      "minmax": [
        1007,
        null
      ],
      "types": {
        "signature": "(Address, MultiSignature, SignedExtra)",
        "Address": "AccountId",
        "AccountIndex": "u32",
        "AccountId": "[u8; 32]",
        "SignedExtra": "(OnlyStakingAndClaims, system::CheckVersion<Runtime>, system::CheckGenesis<Runtime>, system::CheckEra<Runtime>, system::CheckNonce<Runtime>, system::CheckWeight<Runtime>, transaction_payment::ChargeTransactionPayment::<Runtime>, registrar::LimitParathreadCommits<Runtime>)",
        "OnlyStakingAndClaims": "[u8; 0]",
        "system::CheckVersion<Runtime>": "[u8; 0]",
        "system::CheckGenesis<Runtime>": "[u8; 0]",
        "system::CheckEra<Runtime>": "Era",
        "Era": {
          "_enum": {
              "Immortal",
              "Mortal": "(Period, Phase)"
          }
        },
        "Period": "u64",
        "Phase": "u64",
        "system::CheckNonce<Runtime>": "Compact<Index>",
        "system::CheckWeight<Runtime>": "[u8; 0]",
        "transaction_payment::ChargeTransactionPayment::<Runtime>": "BalanceOf",
        "registrar::LimitParathreadCommits<Runtime>": "[u8; 0]"
      }
    }
  ]
}
